README.rst
setup.py
macroecon/__init__.py
macroecon/collect_ipea_series_info.py
macroecon/ipea_indicadores.py
macroecon/ipeadata.py
macroecon/ipeadata_indicadores.py
macroecon.egg-info/PKG-INFO
macroecon.egg-info/SOURCES.txt
macroecon.egg-info/dependency_links.txt
macroecon.egg-info/requires.txt
macroecon.egg-info/top_level.txt
tests/__init__.py
tests/test_sample.py