Metadata-Version: 1.1
Name: macroecon
Version: 0.1.3
Summary: Interface with macroeconomic data sources from Brasil, such as IPEA.
Home-page: https://github.com/pfcor/macroecon.git
Author: Pedro Correia
Author-email: pedrocorreia.rs@gmail.com
License: UNKNOWN
Platform: UNKNOWN
Classifier: Development Status :: 2 - Pre-Alpha
Classifier: Programming Language :: Python
Classifier: Programming Language :: Python :: 3.6
